pixivtools/__init__.py
pixivtools/pixiv_api/__init__.py
pixivtools/pixiv_api/artwork_options.py
pixivtools/pixiv_api/image_urls.py
pixivtools/pixiv_api/struct.py
pixivtools/pixiv_api/utils.py
pixivtools/pixiv_cfg/__init__.py
pixivtools/pixiv_service/__init__.py
pixivtools/pixiv_service/context.py
pixivtools/pixiv_service/crawler.py
pixivtools/pixiv_service/model.py
pixivtools/pixiv_service/service.py
pixivtools/pixiv_utils/__init__.py
pixivtools/pixiv_utils/log.py
pixivtools-0.0.6.dist-info/LICENSE
pixivtools-0.0.6.dist-info/METADATA
pixivtools-0.0.6.dist-info/WHEEL
pixivtools-0.0.6.dist-info/entry_points.txt
pixivtools-0.0.6.dist-info/top_level.txt
pixivtools-0.0.6.dist-info/RECORD
