Metadata-Version: 2.2
Name: pixivtools
Version: 0.0.6
Summary: A Python module for Pixiv crawling and interaction
Home-page: https://github.com/aliubo/pixivtools
Author: aliubo
Author-email: liubo@aliubo.com
Project-URL: Bug Reports, https://github.com/aliubo/pixivtools/issues
Project-URL: Source, https://github.com/aliubo/pixivtools
Keywords: pixiv,crawler,downloader,artwork,illustration
Classifier: Development Status :: 4 - Beta
Classifier: Intended Audience :: Developers
Classifier: Programming Language :: Python :: 3
Classifier: Programming Language :: Python :: 3.6
Classifier: Programming Language :: Python :: 3.7
Classifier: Programming Language :: Python :: 3.8
Classifier: Programming Language :: Python :: 3.9
Classifier: Programming Language :: Python :: 3.10
Classifier: License :: OSI Approved :: MIT License
Classifier: Operating System :: OS Independent
Classifier: Topic :: Internet :: WWW/HTTP
Classifier: Topic :: Software Development :: Libraries :: Python Modules
Requires-Python: >=3.6
License-File: LICENSE
Requires-Dist: parsel
Requires-Dist: Pillow
Requires-Dist: PyYAML
Requires-Dist: Requests
Requires-Dist: SQLAlchemy
Dynamic: author
Dynamic: author-email
Dynamic: classifier
Dynamic: description
Dynamic: description-content-type
Dynamic: home-page
Dynamic: keywords
Dynamic: project-url
Dynamic: requires-dist
Dynamic: requires-python
Dynamic: summary
